crnpy/__init__.py
crnpy/crnpy.py
crnpy/data.py
crnpy-0.6.1.dist-info/LICENSE
crnpy-0.6.1.dist-info/METADATA
crnpy-0.6.1.dist-info/WHEEL
crnpy-0.6.1.dist-info/top_level.txt
crnpy-0.6.1.dist-info/RECORD
