Metadata-Version: 2.1
Name: crnpy
Version: 0.6.1
Summary: A Python package for the estimation and processing of soil moisture data from cosmic-ray neutron counts.
Home-page: https://soilwater.github.io/crnpy/
Author: Joaquin Peraza, Andres Patrignani
Author-email: jperaza@ksu.edu, andrespatrignani@ksu.edu
License: MIT
License-File: LICENSE
Requires-Dist: numpy
Requires-Dist: pandas
Requires-Dist: scipy
Requires-Dist: requests
Requires-Dist: utm
